cmseq/__init__.py
cmseq/breadth_depth.py
cmseq/cmseq.py
cmseq/consensus.py
cmseq/consensus_aDNA.py
cmseq/filter.py
cmseq/poly.py
cmseq/polymut.py
CMSeq-1.0.4.dist-info/LICENSE.txt
CMSeq-1.0.4.dist-info/METADATA
CMSeq-1.0.4.dist-info/WHEEL
CMSeq-1.0.4.dist-info/entry_points.txt
CMSeq-1.0.4.dist-info/top_level.txt
CMSeq-1.0.4.dist-info/RECORD
