Metadata-Version: 2.1
Name: CMSeq
Version: 1.0.4
Summary: Set of utilities on sequences and BAM files
Home-page: http://github.com/SegataLab/cmseq/
Author: Moreno Zolfo
Author-email: moreno.zolfo@unitn.it
License: LICENSE.txt
Platform: UNKNOWN
Requires-Dist: numpy
Requires-Dist: scipy
Requires-Dist: pysam
Requires-Dist: pandas
Requires-Dist: biopython
Requires-Dist: bcbio-gff
